benchmarks/__init__.py
benchmarks/bandwidth/__init__.py
benchmarks/bandwidth/iperf3-client.yaml
benchmarks/bandwidth/iperf3-server.yaml
benchmarks/locust/Dockerfile
benchmarks/locust/README.md
benchmarks/locust/build-image-and-relase.sh
benchmarks/locust/client-locust.yaml
benchmarks/locust/locustfile.py
benchmarks/locust/server-locust.yaml
k8perf/__init__.py
k8perf/__main__.py
k8perf/_version.py
k8perf/benchmark.py
k8perf/benchmarks.py
k8perf/kubernetes_integration.py
k8perf/util_logging.py
k8perf/util_terminal_ui.py
k8perf/util_yaml.py
k8perf-1.0.2.dist-info/LICENSE
k8perf-1.0.2.dist-info/METADATA
k8perf-1.0.2.dist-info/WHEEL
k8perf-1.0.2.dist-info/entry_points.txt
k8perf-1.0.2.dist-info/top_level.txt
k8perf-1.0.2.dist-info/RECORD
