Metadata-Version: 2.1
Name: k8perf
Version: 1.0.2
Summary: A kubernetes network performance testing tool
Author-email: Anders Aaen Springborg <aaspringborg@gmail.com>
Project-URL: Homepage, https://github.com/radioactivebean0/cse291-cloud-network-benchmark
Project-URL: Bug Tracker, https://github.com/radioactivebean0/cse291-cloud-network-benchmark/issues
Classifier: Programming Language :: Python :: 3
Classifier: Programming Language :: Python :: 3.9
Classifier: Programming Language :: Python :: 3.10
Classifier: Programming Language :: Python :: 3.11
Classifier: License :: OSI Approved :: MIT License
Classifier: Operating System :: OS Independent
Classifier: Topic :: System :: Networking
Requires-Python: >=3.9
License-File: LICENSE
Requires-Dist: typer
Requires-Dist: kubernetes
Requires-Dist: rich
Requires-Dist: InquirerPy
Requires-Dist: uplink
Requires-Dist: PyYAML
Requires-Dist: setuptools-scm
Requires-Dist: matplotlib
Requires-Dist: seaborn
Provides-Extra: dev
Requires-Dist: pytest (>=6.2.5) ; extra == 'dev'
Requires-Dist: regex ; extra == 'dev'
Requires-Dist: tox ; extra == 'dev'
